<?xml version="1.0" encoding="UTF-8"?>
<persistence version="2.0"
	xmlns="http://java.sun.com/xml/ns/persistence" xmlns:xsi="http://www.w3.org/2001/XMLSchema-instance"
	xsi:schemaLocation="http://java.sun.com/xml/ns/persistence http://java.sun.com/xml/ns/persistence/persistence_2_0.xsd">
	<persistence-unit name="ads-backend">
		<class>com.netapp.ads.models.Activity</class>
		<class>com.netapp.ads.models.ActivityLobXRef</class>
		<class>com.netapp.ads.models.ActivityLobXRefPK</class>
		<class>com.netapp.ads.models.ActivityMigrationKeyXRef</class>
		<class>com.netapp.ads.models.ActivityMigrationKeyXRefPK</class>
		<class>com.netapp.ads.models.ActivityPresumedLobXRef</class>
		<class>com.netapp.ads.models.ActivityPresumedLobXRefPK</class>
		<class>com.netapp.ads.models.ActivityResponse</class>
		<class>com.netapp.ads.models.ActivityResponsePK</class>
		<class>com.netapp.ads.models.Aggregate</class>
		<class>com.netapp.ads.models.AggregatePK</class>
		<class>com.netapp.ads.models.AggregatePurpose</class>
		<class>com.netapp.ads.models.AggregatePurposePK</class>
		<class>com.netapp.ads.models.Application</class>
		<class>com.netapp.ads.models.ApplicationLobXRef</class>
		<class>com.netapp.ads.models.ApplicationLobXRefPK</class>
		<class>com.netapp.ads.models.AuditEvent</class>
		<class>com.netapp.ads.models.AuditReasonCode</class>
		<class>com.netapp.ads.models.AuditReasonCodePK</class>
		<class>com.netapp.ads.models.AuditTrailApi</class>
		<class>com.netapp.ads.models.AuditTrailApiPK</class>
		<class>com.netapp.ads.models.AuditTrailCorporateUser</class>
		<class>com.netapp.ads.models.AuditTrailCorporateUserPK</class>
		<class>com.netapp.ads.models.AuditTrailNativeUser</class>
		<class>com.netapp.ads.models.AuditTrailNativeUserPK</class>
		<class>com.netapp.ads.models.ChangeManagement</class>
		<class>com.netapp.ads.models.ChangeManagementPK</class>
		<class>com.netapp.ads.models.Controller</class>
		<class>com.netapp.ads.models.ControllerPK</class>
		<class>com.netapp.ads.models.Cutover</class>
		<class>com.netapp.ads.models.CutoverPK</class>
		<class>com.netapp.ads.models.CutoverAssembly</class>
		<class>com.netapp.ads.models.CutoverAssemblyPK</class>
		<class>com.netapp.ads.models.CutoverMountPoint</class>
		<class>com.netapp.ads.models.CutoverTime</class>
		<class>com.netapp.ads.models.CutoverTimePK</class>
		<class>com.netapp.ads.models.DataCenter</class>
		<class>com.netapp.ads.models.DataProtectionPolicy</class>
		<class>com.netapp.ads.models.EmailTemplate</class>
		<class>com.netapp.ads.models.Export</class>
		<class>com.netapp.ads.models.ExportsHostXRef</class>
		<class>com.netapp.ads.models.ExportsHostXRefPK</class>
		<class>com.netapp.ads.models.ExtendedInfoVarchar</class>
		<class>com.netapp.ads.models.ExtendedInfoVarcharSetting</class>
		<class>com.netapp.ads.models.Host</class>
		<class>com.netapp.ads.models.HostApplicationXRef</class>
		<class>com.netapp.ads.models.HostApplicationXRefPK</class>
		<class>com.netapp.ads.models.Ical</class>
		<class>com.netapp.ads.models.IcalPK</class>
		<class>com.netapp.ads.models.LineOfBusiness</class>
		<class>com.netapp.ads.models.MigrationCutoverEvent</class>
		<class>com.netapp.ads.models.MigrationCutoverSrcToTgt</class>
		<class>com.netapp.ads.models.MigrationCutoverSrcToTgtPK</class>
		<class>com.netapp.ads.models.MigrationCutoverTeam</class>
		<class>com.netapp.ads.models.MigrationKey</class>
		<class>com.netapp.ads.models.MigrationProject</class>
		<class>com.netapp.ads.models.MigrationTime</class>
		<class>com.netapp.ads.models.MmsConfig</class>
		<class>com.netapp.ads.models.MmsPropertyType</class>
		<class>com.netapp.ads.models.MountPoint</class>
		<class>com.netapp.ads.models.MountPointPK</class>
		<class>com.netapp.ads.models.MstEmailType</class>
		<class>com.netapp.ads.models.MstEmailingDate</class>
		<class>com.netapp.ads.models.MstEmailingDatePK</class>
		<class>com.netapp.ads.models.NasVolume</class>
		<class>com.netapp.ads.models.Qtree</class>
		<class>com.netapp.ads.models.Replication</class>
		<class>com.netapp.ads.models.ReplicationPK</class>
		<class>com.netapp.ads.models.Schedule</class>
		<class>com.netapp.ads.models.ScheduleReset</class>
		<class>com.netapp.ads.models.SchemaVersion</class>
		<class>com.netapp.ads.models.Share</class>
		<class>com.netapp.ads.models.SharePK</class>
		<class>com.netapp.ads.models.SourceStorage</class>
		<class>com.netapp.ads.models.Storage</class>
		<class>com.netapp.ads.models.Storagex</class>
		<class>com.netapp.ads.models.StoragexPK</class>
		<class>com.netapp.ads.models.SystemAdmin</class>
		<class>com.netapp.ads.models.SystemAdminPK</class>
		<class>com.netapp.ads.models.User</class>
		<class>com.netapp.ads.models.UserApi</class>
		<class>com.netapp.ads.models.UserCorporate</class>
		<class>com.netapp.ads.models.UserNative</class>
		<class>com.netapp.ads.models.UserRole</class>
		<class>com.netapp.ads.models.WfaData</class>
		<class>com.netapp.ads.models.WfaDataPK</class>
		<class>com.netapp.ads.models.WfaMessage</class>
		<class>com.netapp.ads.models.WfaMessagePK</class>
		<class>com.netapp.ads.models.WfaOcumControllerData</class>
		<class>com.netapp.ads.models.WorkPackage</class>
		<class>com.netapp.ads.models.Workflow</class>
		<class>com.netapp.ads.models.WorkflowPK</class>
	</persistence-unit>
	
</persistence>